{
  "items": [
     {
        "tags": [
           "c#",
           "mysql",
           ".net"
        ],
        "owner": {
           "reputation": 92,
           "user_id": 9784267,
           "user_type": "registered",
           "profile_image": "https://www.gravatar.com/avatar/8e5600b97435533105a84bd4d07a1a21?s=128&d=identicon&r=PG&f=1",
           "display_name": "Micheal Choudhary",
           "link": "https://stackoverflow.com/users/9784267/micheal-choudhary"
        },
        "is_answered": false,
        "view_count": 31,
        "answer_count": 0,
        "score": -2,
        "last_activity_date": 1534278366,
        "creation_date": 1534274238,
        "last_edit_date": 1534278366,
        "question_id": 51848391,
        "link": "https://stackoverflow.com/questions/51848391/add-application-name-in-mysql-connection-string",
        "title": "Add Application Name in mysql connection string"
     },
     {
        "tags": [
           "php"
        ],
        "owner": {
           "reputation": 1,
           "user_id": 10226477,
           "user_type": "registered",
           "profile_image": "https://www.gravatar.com/avatar/c223e8441b577181c50bc62bc4d3d2fd?s=128&d=identicon&r=PG&f=1",
           "display_name": "JBM",
           "link": "https://stackoverflow.com/users/10226477/jbm"
        },
        "is_answered": true,
        "view_count": 17,
        "answer_count": 1,
        "score": 0,
        "last_activity_date": 1534278366,
        "creation_date": 1534277374,
        "last_edit_date": 1534278366,
        "question_id": 51849060,
        "link": "https://stackoverflow.com/questions/51849060/php-has-no-setlogmask",
        "title": "PHP has no setlogmask?"
     },
     {
        "tags": [
           "xamarin.forms"
        ],
        "owner": {
           "reputation": 454,
           "user_id": 1136506,
           "user_type": "registered",
           "accept_rate": 86,
           "profile_image": "https://www.gravatar.com/avatar/065dcdba52a57c9c83b2c21a7775fe2b?s=128&d=identicon&r=PG",
           "display_name": "Darius",
           "link": "https://stackoverflow.com/users/1136506/darius"
        },
        "is_answered": false,
        "view_count": 2,
        "answer_count": 0,
        "score": 0,
        "last_activity_date": 1534278360,
        "creation_date": 1534278360,
        "question_id": 51849275,
        "link": "https://stackoverflow.com/questions/51849275/use-custom-renderer-on-only-one-entry-control",
        "title": "Use custom renderer on only one Entry control"
     },
     {
        "tags": [
           "sql-server",
           "view",
           "user-defined-functions"
        ],
        "owner": {
           "reputation": 6,
           "user_id": 10082815,
           "user_type": "registered",
           "profile_image": "https://www.gravatar.com/avatar/cfb315a72bb6e826ffdf0caaab52d20b?s=128&d=identicon&r=PG&f=1",
           "display_name": "Javascripttech",
           "link": "https://stackoverflow.com/users/10082815/javascripttech"
        },
        "is_answered": true,
        "view_count": 39,
        "answer_count": 1,
        "score": -1,
        "last_activity_date": 1534278357,
        "creation_date": 1534105278,
        "last_edit_date": 1534278357,
        "question_id": 51812521,
        "link": "https://stackoverflow.com/questions/51812521/user-defined-function-sql-error",
        "title": "User Defined Function SQL Error"
     },
     {
        "tags": [
           "python",
           "python-3.x",
           "pandas",
           "dataframe",
           "data-manipulation"
        ],
        "owner": {
           "reputation": 25,
           "user_id": 7851623,
           "user_type": "registered",
           "profile_image": "https://www.gravatar.com/avatar/469f5a9f1b21d5097a7b3e4dd4a767df?s=128&d=identicon&r=PG&f=1",
           "display_name": "aguntuk",
           "link": "https://stackoverflow.com/users/7851623/aguntuk"
        },
        "is_answered": false,
        "view_count": 27,
        "answer_count": 3,
        "score": 0,
        "last_activity_date": 1534278356,
        "creation_date": 1534276935,
        "question_id": 51848977,
        "link": "https://stackoverflow.com/questions/51848977/data-formatting-and-manipulation-in-python",
        "title": "Data formatting and manipulation in Python"
     },
     {
        "tags": [
           "matplotlib"
        ],
        "owner": {
           "reputation": 1128,
           "user_id": 1856725,
           "user_type": "registered",
           "accept_rate": 64,
           "profile_image": "https://www.gravatar.com/avatar/b4caeb900ea00f81013ba8e310dba94b?s=128&d=identicon&r=PG",
           "display_name": "Iron Pillow",
           "link": "https://stackoverflow.com/users/1856725/iron-pillow"
        },
        "is_answered": false,
        "view_count": 2,
        "answer_count": 0,
        "score": 0,
        "last_activity_date": 1534278351,
        "creation_date": 1534278351,
        "question_id": 51849273,
        "link": "https://stackoverflow.com/questions/51849273/matplotlib-how-to-plot-text-in-corner-of-paper-canvas-not-corner-of-plot",
        "title": "Matplotlib: How to plot text in corner of paper/canvas (not corner of plot)"
     },
     {
        "tags": [
           "r",
           "date"
        ],
        "owner": {
           "reputation": 1,
           "user_id": 10001170,
           "user_type": "registered",
           "profile_image": "https://www.gravatar.com/avatar/bc8aca795a9d4065fdeb8864c048bc2c?s=128&d=identicon&r=PG&f=1",
           "display_name": "zhshzh44",
           "link": "https://stackoverflow.com/users/10001170/zhshzh44"
        },
        "is_answered": false,
        "view_count": 9,
        "answer_count": 1,
        "score": 0,
        "last_activity_date": 1534278351,
        "creation_date": 1534277689,
        "question_id": 51849116,
        "link": "https://stackoverflow.com/questions/51849116/date-converting-in-r",
        "title": "Date Converting in R"
     },
     {
        "tags": [
           "typescript",
           "types"
        ],
        "owner": {
           "reputation": 15812,
           "user_id": 454780,
           "user_type": "registered",
           "accept_rate": 78,
           "profile_image": "https://www.gravatar.com/avatar/d8238ae773f9d75e510abe305209189f?s=128&d=identicon&r=PG",
           "display_name": "trusktr",
           "link": "https://stackoverflow.com/users/454780/trusktr"
        },
        "is_answered": false,
        "view_count": 10,
        "answer_count": 0,
        "score": 0,
        "last_activity_date": 1534278344,
        "creation_date": 1534277700,
        "last_edit_date": 1534278344,
        "question_id": 51849119,
        "link": "https://stackoverflow.com/questions/51849119/does-typescript-jsdoc-style-typing-have-full-power-of-regular-types",
        "title": "Does TypeScript JSDoc-style typing have full power of regular types?"
     },
     {
        "tags": [
           "aws-cli"
        ],
        "owner": {
           "reputation": 8,
           "user_id": 4912221,
           "user_type": "registered",
           "profile_image": "https://www.gravatar.com/avatar/8504fbbbea74ea3da2115e1a0c6682a7?s=128&d=identicon&r=PG&f=1",
           "display_name": "Aish Mahesh",
           "link": "https://stackoverflow.com/users/4912221/aish-mahesh"
        },
        "is_answered": false,
        "view_count": 2,
        "answer_count": 0,
        "score": 0,
        "last_activity_date": 1534278340,
        "creation_date": 1534278340,
        "question_id": 51849271,
        "link": "https://stackoverflow.com/questions/51849271/aws-cli-for-searching-a-file-in-s3-bucket",
        "title": "AWS CLI for searching a file in s3 bucket"
     },
     {
        "tags": [
           "python",
           "pandas",
           "pandas-groupby"
        ],
        "owner": {
           "reputation": 58,
           "user_id": 4067744,
           "user_type": "registered",
           "profile_image": "https://lh5.googleusercontent.com/-hh_wsynDQV8/AAAAAAAAAAI/AAAAAAAAAnU/PwSg_0RdiG4/photo.jpg?sz=128",
           "display_name": "Wael Hussein",
           "link": "https://stackoverflow.com/users/4067744/wael-hussein"
        },
        "is_answered": false,
        "view_count": 11,
        "answer_count": 1,
        "score": 1,
        "last_activity_date": 1534278338,
        "creation_date": 1534278003,
        "last_edit_date": 1534278041,
        "question_id": 51849186,
        "link": "https://stackoverflow.com/questions/51849186/when-using-pandas-groupby-why-use-agg-versus-directly-using-the-function-eg",
        "title": "When using Pandas .groupby, why use .agg versus directly using the function eg .sum()"
     },
     {
        "tags": [
           "c#",
           "asp.net-core"
        ],
        "owner": {
           "reputation": 2620,
           "user_id": 1319512,
           "user_type": "registered",
           "accept_rate": 59,
           "profile_image": "https://www.gravatar.com/avatar/e4dcee68ab221665358897d6f67800b2?s=128&d=identicon&r=PG",
           "display_name": "Marco",
           "link": "https://stackoverflow.com/users/1319512/marco"
        },
        "is_answered": true,
        "view_count": 18,
        "answer_count": 1,
        "score": 1,
        "last_activity_date": 1534278338,
        "creation_date": 1534252417,
        "last_edit_date": 1534278338,
        "question_id": 51842370,
        "link": "https://stackoverflow.com/questions/51842370/routes-are-not-initialized",
        "title": "Routes are not initialized"
     },
     {
        "tags": [
           "html",
           "css",
           "css-grid"
        ],
        "owner": {
           "reputation": 1401,
           "user_id": 1332416,
           "user_type": "registered",
           "accept_rate": 94,
           "profile_image": "https://www.gravatar.com/avatar/9450fd5b9a7bd3d776823f86c4caf1cb?s=128&d=identicon&r=PG",
           "display_name": "Veksi",
           "link": "https://stackoverflow.com/users/1332416/veksi"
        },
        "is_answered": false,
        "view_count": 3,
        "answer_count": 0,
        "score": 0,
        "last_activity_date": 1534278336,
        "creation_date": 1534278336,
        "question_id": 51849269,
        "link": "https://stackoverflow.com/questions/51849269/how-to-auto-expand-css-grid-cells-to-fill-available-space-when-it-is-centered",
        "title": "How to &quot;auto-expand&quot; CSS grid cells to fill available space when it is centered?"
     },
     {
        "tags": [
           "javascript",
           "typescript",
           "momentjs"
        ],
        "owner": {
           "reputation": 392,
           "user_id": 319470,
           "user_type": "registered",
           "accept_rate": 77,
           "profile_image": "https://www.gravatar.com/avatar/0717c876ea92548f472c74eee903d2d5?s=128&d=identicon&r=PG",
           "display_name": "KSwift87",
           "link": "https://stackoverflow.com/users/319470/kswift87"
        },
        "is_answered": false,
        "view_count": 33,
        "answer_count": 1,
        "score": -3,
        "last_activity_date": 1534278335,
        "creation_date": 1534276608,
        "question_id": 51848906,
        "link": "https://stackoverflow.com/questions/51848906/why-does-moment-format-create-a-date-object-six-hours-in-the-future",
        "title": "Why does moment().format() create a date object six hours in the future?"
     },
     {
        "tags": [
           "ruby"
        ],
        "owner": {
           "reputation": 1583,
           "user_id": 4501354,
           "user_type": "registered",
           "accept_rate": 65,
           "profile_image": "https://www.gravatar.com/avatar/1230cfcc7f68488ad19d0022cf7b1a93?s=128&d=identicon&r=PG&f=1",
           "display_name": "Donato",
           "link": "https://stackoverflow.com/users/4501354/donato"
        },
        "is_answered": false,
        "view_count": 6,
        "answer_count": 1,
        "score": 0,
        "last_activity_date": 1534278331,
        "creation_date": 1534276775,
        "question_id": 51848944,
        "link": "https://stackoverflow.com/questions/51848944/make-nested-modules-available-globally",
        "title": "Make nested modules available globally"
     },
     {
        "tags": [
           "django",
           "timezone",
           "django-orm",
           "pytz",
           "django-timezone"
        ],
        "owner": {
           "reputation": 9637,
           "user_id": 1888983,
           "user_type": "registered",
           "accept_rate": 49,
           "profile_image": "https://i.stack.imgur.com/Y6tnm.png?s=128&g=1",
           "display_name": "jozxyqk",
           "link": "https://stackoverflow.com/users/1888983/jozxyqk"
        },
        "is_answered": false,
        "view_count": 2,
        "answer_count": 0,
        "score": 0,
        "last_activity_date": 1534278322,
        "creation_date": 1534278322,
        "question_id": 51849266,
        "link": "https://stackoverflow.com/questions/51849266/django-orm-returning-timezone-unaware-datetime",
        "title": "Django ORM returning timezone unaware datetime"
     },
     {
        "tags": [
           "linux",
           "bash",
           "shell",
           "unix",
           "zsh"
        ],
        "owner": {
           "reputation": 5,
           "user_id": 8413951,
           "user_type": "registered",
           "profile_image": "https://i.stack.imgur.com/kZXpW.gif?s=128&g=1",
           "display_name": "Bitfighter",
           "link": "https://stackoverflow.com/users/8413951/bitfighter"
        },
        "is_answered": false,
        "view_count": 4,
        "answer_count": 0,
        "score": 0,
        "last_activity_date": 1534278319,
        "creation_date": 1534278319,
        "question_id": 51849265,
        "link": "https://stackoverflow.com/questions/51849265/what-is-the-difference-between-bash-and-zsh",
        "title": "What is the difference between Bash and Zsh?"
     },
     {
        "tags": [
           "javascript",
           "json",
           "node.js",
           "websocket",
           "stream"
        ],
        "owner": {
           "reputation": 8829,
           "user_id": 1650012,
           "user_type": "registered",
           "accept_rate": 67,
           "profile_image": "https://www.gravatar.com/avatar/a21bc05bb7df4e5c3cb4933e4f3072eb?s=128&d=identicon&r=PG",
           "display_name": "kramer65",
           "link": "https://stackoverflow.com/users/1650012/kramer65"
        },
        "is_answered": true,
        "view_count": 336,
        "bounty_amount": 500,
        "bounty_closes_date": 1534339169,
        "answer_count": 7,
        "score": 15,
        "last_activity_date": 1534278319,
        "creation_date": 1533546623,
        "last_edit_date": 1533836394,
        "question_id": 51704138,
        "link": "https://stackoverflow.com/questions/51704138/how-to-handle-weirdly-combined-websocket-messages",
        "title": "How to handle weirdly combined websocket messages?"
     },
     {
        "tags": [
           "swift",
           "avcapturemoviefileoutput"
        ],
        "owner": {
           "reputation": 110,
           "user_id": 9246850,
           "user_type": "registered",
           "accept_rate": 67,
           "profile_image": "https://www.gravatar.com/avatar/09d16125f5c94fc2cafc66788579b32b?s=128&d=identicon&r=PG&f=1",
           "display_name": "Andras Karpati",
           "link": "https://stackoverflow.com/users/9246850/andras-karpati"
        },
        "is_answered": true,
        "view_count": 12,
        "accepted_answer_id": 51832599,
        "answer_count": 1,
        "score": 0,
        "last_activity_date": 1534278314,
        "creation_date": 1534184950,
        "question_id": 51828494,
        "link": "https://stackoverflow.com/questions/51828494/getting-image-from-avcapturemoviefileoutput-without-switching",
        "title": "Getting image from AVCaptureMovieFileOutput without switching"
     },
     {
        "tags": [
           "python-3.x",
           "function",
           "loops"
        ],
        "owner": {
           "reputation": 23,
           "user_id": 9811216,
           "user_type": "registered",
           "profile_image": "https://www.gravatar.com/avatar/f47a49d933c759fe89eb3c485813077b?s=128&d=identicon&r=PG&f=1",
           "display_name": "SolingerMUC",
           "link": "https://stackoverflow.com/users/9811216/solingermuc"
        },
        "is_answered": false,
        "view_count": 2,
        "answer_count": 0,
        "score": 0,
        "last_activity_date": 1534278312,
        "creation_date": 1534278312,
        "question_id": 51849263,
        "link": "https://stackoverflow.com/questions/51849263/loop-over-set-of-functions-for-variable-pipelining-and-separate-usage",
        "title": "Loop over Set of Functions for Variable Pipelining and Separate Usage"
     },
     {
        "tags": [
           "r"
        ],
        "owner": {
           "reputation": 5,
           "user_id": 6706438,
           "user_type": "registered",
           "profile_image": "https://www.gravatar.com/avatar/8520281388913ed1d9793808156c90de?s=128&d=identicon&r=PG&f=1",
           "display_name": "D. Bryant",
           "link": "https://stackoverflow.com/users/6706438/d-bryant"
        },
        "is_answered": false,
        "view_count": 13,
        "answer_count": 1,
        "score": 0,
        "last_activity_date": 1534278305,
        "creation_date": 1534275200,
        "question_id": 51848604,
        "link": "https://stackoverflow.com/questions/51848604/r-calculating-a-running-total-between-different-time-intervals",
        "title": "R - Calculating a Running Total Between Different Time Intervals"
     },
     {
        "tags": [
           "css"
        ],
        "owner": {
           "reputation": 650,
           "user_id": 5357758,
           "user_type": "registered",
           "accept_rate": 56,
           "profile_image": "https://www.gravatar.com/avatar/266d83febb1a6e98f03837ea1ad3c411?s=128&d=identicon&r=PG&f=1",
           "display_name": "yavg",
           "link": "https://stackoverflow.com/users/5357758/yavg"
        },
        "is_answered": false,
        "view_count": 4,
        "answer_count": 0,
        "score": 0,
        "last_activity_date": 1534278304,
        "creation_date": 1534278304,
        "question_id": 51849261,
        "link": "https://stackoverflow.com/questions/51849261/perform-animation-pulse-to-an-icon-using-css",
        "title": "perform animation &quot;pulse&quot;, to an icon using css"
     },
     {
        "tags": [
           "c#",
           "asp.net",
           "model-view-controller",
           "httpclient"
        ],
        "owner": {
           "reputation": 1,
           "user_id": 10204361,
           "user_type": "registered",
           "profile_image": "https://lh4.googleusercontent.com/-WVSKbPknwhk/AAAAAAAAAAI/AAAAAAAAAAA/AAnnY7paXYePzRiluFUJdI5CLtlS-0fY2Q/mo/photo.jpg?sz=128",
           "display_name": "Luis Rodriguez",
           "link": "https://stackoverflow.com/users/10204361/luis-rodriguez"
        },
        "is_answered": false,
        "view_count": 9,
        "answer_count": 0,
        "score": -1,
        "last_activity_date": 1534278301,
        "creation_date": 1534257738,
        "last_edit_date": 1534278301,
        "question_id": 51844072,
        "link": "https://stackoverflow.com/questions/51844072/content-is-being-disposed-because-of-the-content-size-httpclient-post-request",
        "title": "Content is being disposed because of the content size HttpClient POST request"
     },
     {
        "tags": [
           "spring",
           "spring-security",
           "spring-security-oauth2"
        ],
        "owner": {
           "reputation": 8461,
           "user_id": 650176,
           "user_type": "registered",
           "accept_rate": 76,
           "profile_image": "https://www.gravatar.com/avatar/4dd2e81ba25c27e9ee18d547c4761c59?s=128&d=identicon&r=PG",
           "display_name": "David V",
           "link": "https://stackoverflow.com/users/650176/david-v"
        },
        "is_answered": false,
        "view_count": 2,
        "answer_count": 0,
        "score": 0,
        "last_activity_date": 1534278299,
        "creation_date": 1534278299,
        "question_id": 51849260,
        "link": "https://stackoverflow.com/questions/51849260/mapping-oauth2-login-to-custom-principal",
        "title": "Mapping OAuth2 Login to custom Principal"
     },
     {
        "tags": [
           "javascript",
           "python",
           "html",
           "flask"
        ],
        "owner": {
           "reputation": 1,
           "user_id": 9081786,
           "user_type": "registered",
           "profile_image": "https://www.gravatar.com/avatar/600c707d0d93bf9443610893c7ac3328?s=128&d=identicon&r=PG&f=1",
           "display_name": "Riley",
           "link": "https://stackoverflow.com/users/9081786/riley"
        },
        "is_answered": false,
        "view_count": 9,
        "answer_count": 0,
        "score": -1,
        "last_activity_date": 1534278298,
        "creation_date": 1534277664,
        "last_edit_date": 1534278298,
        "question_id": 51849112,
        "link": "https://stackoverflow.com/questions/51849112/general-flask-when-to-use-javascript-vs-using-post-get-and-a-python-defined-fun",
        "title": "General Flask: When to use javascript vs using POST/GET and a python defined function"
     },
     {
        "tags": [
           "jquery"
        ],
        "owner": {
           "reputation": 8,
           "user_id": 9540044,
           "user_type": "registered",
           "profile_image": "https://www.gravatar.com/avatar/0640e178b51eed2e45bc985ae1d3b052?s=128&d=identicon&r=PG&f=1",
           "display_name": "nriit",
           "link": "https://stackoverflow.com/users/9540044/nriit"
        },
        "is_answered": true,
        "view_count": 17,
        "accepted_answer_id": 51847321,
        "answer_count": 1,
        "score": 1,
        "last_activity_date": 1534278289,
        "creation_date": 1534269240,
        "last_edit_date": 1534278289,
        "question_id": 51847224,
        "link": "https://stackoverflow.com/questions/51847224/on-click-not-changing-the-background-color-of-button",
        "title": "On click not changing the background color of button"
     },
     {
        "tags": [
           "css",
           "css3",
           "css-shapes"
        ],
        "owner": {
           "reputation": 14356,
           "user_id": 2405040,
           "user_type": "registered",
           "accept_rate": 82,
           "profile_image": "https://www.gravatar.com/avatar/d2bf93a27e5ec1bb8b6fdb063972b275?s=128&d=identicon&r=PG",
           "display_name": "Shashank Agrawal",
           "link": "https://stackoverflow.com/users/2405040/shashank-agrawal"
        },
        "is_answered": false,
        "view_count": 24,
        "answer_count": 1,
        "score": 2,
        "last_activity_date": 1534278288,
        "creation_date": 1534269890,
        "last_edit_date": 1534278288,
        "question_id": 51847370,
        "link": "https://stackoverflow.com/questions/51847370/adding-3d-effect-on-image-with-css",
        "title": "Adding 3D effect on image with CSS"
     },
     {
        "tags": [
           "ilnumerics"
        ],
        "owner": {
           "reputation": 1,
           "user_id": 10213085,
           "user_type": "registered",
           "profile_image": "https://www.gravatar.com/avatar/0ebc633f5da457eafae94952b04261e1?s=128&d=identicon&r=PG&f=1",
           "display_name": "Dave R",
           "link": "https://stackoverflow.com/users/10213085/dave-r"
        },
        "is_answered": false,
        "view_count": 2,
        "answer_count": 0,
        "score": 0,
        "last_activity_date": 1534278287,
        "creation_date": 1534278287,
        "question_id": 51849259,
        "link": "https://stackoverflow.com/questions/51849259/updating-z-values-for-ilsurface",
        "title": "Updating z-values for ILSurface"
     },
     {
        "tags": [
           "django",
           "django-rest-framework",
           "django-rest-viewsets",
           "drf-queryset"
        ],
        "owner": {
           "reputation": 11,
           "user_id": 6368082,
           "user_type": "registered",
           "profile_image": "https://www.gravatar.com/avatar/e2b6e815d1278ffb4f812f0556b9896b?s=128&d=identicon&r=PG&f=1",
           "display_name": "rkm2",
           "link": "https://stackoverflow.com/users/6368082/rkm2"
        },
        "is_answered": false,
        "view_count": 13,
        "answer_count": 1,
        "score": 0,
        "last_activity_date": 1534278287,
        "creation_date": 1534274654,
        "last_edit_date": 1534277747,
        "question_id": 51848485,
        "link": "https://stackoverflow.com/questions/51848485/drf-viewset-returns-queryset-with-empty-values",
        "title": "DRF ViewSet Returns QuerySet With Empty Values"
     },
     {
        "tags": [
           "android",
           "fragment",
           "cardview"
        ],
        "owner": {
           "reputation": 16,
           "user_id": 8204270,
           "user_type": "registered",
           "accept_rate": 43,
           "profile_image": "https://www.gravatar.com/avatar/39f5ff548717f633986612ecfa3caa72?s=128&d=identicon&r=PG&f=1",
           "display_name": "Los Kayos",
           "link": "https://stackoverflow.com/users/8204270/los-kayos"
        },
        "is_answered": false,
        "view_count": 4,
        "answer_count": 0,
        "score": 0,
        "last_activity_date": 1534278284,
        "creation_date": 1534278284,
        "question_id": 51849257,
        "link": "https://stackoverflow.com/questions/51849257/gridlayout-with-cardview-in-fragment",
        "title": "GridLayout with CardView in Fragment"
     },
     {
        "tags": [
           "ionic-framework"
        ],
        "owner": {
           "reputation": 1,
           "user_id": 10226108,
           "user_type": "registered",
           "profile_image": "https://www.gravatar.com/avatar/296ea0f7dabc7b865183a889bb006116?s=128&d=identicon&r=PG&f=1",
           "display_name": "Zineb",
           "link": "https://stackoverflow.com/users/10226108/zineb"
        },
        "is_answered": false,
        "view_count": 3,
        "answer_count": 0,
        "score": 0,
        "last_activity_date": 1534278282,
        "creation_date": 1534278282,
        "question_id": 51849256,
        "link": "https://stackoverflow.com/questions/51849256/ionic3-app-checking-values-on-click-button-or-at-ion-input",
        "title": "ionic3 app : checking values on (click) button or at &lt;ion-input&gt;"
     }
  ],
  "has_more": true,
  "quota_max": 300,
  "quota_remaining": 299
}